{"title":"References","markdown":{"headingText":"References","headingAttr":{"id":"","classes":["unnumbered"],"keyvalue":[]},"containsRefs":true,"markdown":"\n::: {#refs}\n@article{knuth84, author = {Knuth, Donald E.}, title = {Literate Programming}, year = {1984}, issue_date = {May 1984}, publisher = {Oxford University Press, Inc.}, address = {USA}, volume = {27}, number = {2}, issn = {0010-4620}, url = {[https://doi.org/10.1093/comjnl/27.2.97},](https://doi.org/10.1093/comjnl/27.2.97},) doi = {10.1093/comjnl/27.2.97}, journal = {Comput. J.}, month = may, pages = {97–111}, numpages = {15} }\n\n@book{kerle2004, title = {Principles of remote sensing: an introductory textbook}, author = {Kerle, Norman and Janssen, Lucas and Bakker, Wim H.}, year = {2004}, date = {2004}, publisher = {The International Institute for Geo-Information Science and Earth Observation (ITC)}, edition = {3rd ed}, note = {OCLC: 66027040}, address = {Enschede}, langid = {en} }\n\n@book{butcher2016, title = {Tour of the electromagnetic spectrum}, author = {Butcher, Ginger}, year = {2016}, date = {2016}, publisher = {National Aeronautics and Space Administration}, edition = {Third edition}, note = {OCLC: 954763341}, address = {Washington, DC}, langid = {en} }\n\n@book{jensen2016, title = {Introductory digital image processing: a remote sensing perspective}, author = {Jensen, John R.}, year = {2016}, date = {2016}, publisher = {Pearson Education}, series = {Pearson series in geographic information science}, edition = {Fourth edition}, address = {Glenview, Ill}, langid = {eng} }\n\n@article{robinson2022, title = {Urban centre green metrics in Great Britain: A geospatial and socioecological study}, author = {Robinson, Jake M. and Mavoa, Suzanne and Robinson, Kate and Brindley, Paul}, editor = {Ustaoglu, Eda}, year = {2022}, month = {11}, date = {2022-11-23}, journal = {PLOS ONE}, pages = {e0276962}, volume = {17}, number = {11}, doi = {10.1371/journal.pone.0276962}, url = {[https://dx.plos.org/10.1371/journal.pone.0276962},](https://dx.plos.org/10.1371/journal.pone.0276962},) langid = {en} }\n\n@book{jensen2016a, title = {Introductory digital image processing: a remote sensing perspective}, author = {Jensen, John R.}, year = {2016}, date = {2016}, publisher = {Pearson Education}, series = {Pearson series in geographic information science}, edition = {Fourth edition}, address = {Glenview, Ill}, langid = {eng} }\n\n@misc{majorsu, title = {Major Summer Heat Spots using Landsat-8 Thermal Satellite data - London Datastore}, url = {[https://data.london.gov.uk/dataset/major-summer-heat-spots-using-landsat-8-thermal-satellite-data-epoqw},](https://data.london.gov.uk/dataset/major-summer-heat-spots-using-landsat-8-thermal-satellite-data-epoqw},) langid = {canadian} }\n\n@misc{londone, title = {London Environment Strategy \\| London City Hall}, url = {[https://www.london.gov.uk/programmes-and-strategies/environment-and-climate-change/london-environment-strategy},](https://www.london.gov.uk/programmes-and-strategies/environment-and-climate-change/london-environment-strategy},) langid = {en-gb} }\n\n@misc{majorsua, title = {Major Summer Heat Spots using Landsat-8 Thermal Satellite data - London Datastore}, url = {[https://data.london.gov.uk/dataset/major-summer-heat-spots-using-landsat-8-thermal-satellite-data-epoqw},](https://data.london.gov.uk/dataset/major-summer-heat-spots-using-landsat-8-thermal-satellite-data-epoqw},) langid = {canadian} }\n\n@book{kerle2004a, title = {Principles of remote sensing: an introductory textbook}, author = {Kerle, Norman and Janssen, Lucas and Bakker, Wim H.}, year = {2004}, date = {2004}, publisher = {The International Institute for Geo-Information Science and Earth Observation (ITC)}, edition = {3rd ed}, note = {OCLC: 66027040}, address = {Enschede}, langid = {en} }\n\n@book{jensen2016b, title = {Introductory digital image processing: a remote sensing perspective}, author = {Jensen, John R.}, year = {2016}, date = {2016}, publisher = {Pearson Education}, series = {Pearson series in geographic information science}, edition = {Fourth edition}, address = {Glenview, Ill}, langid = {eng} }\n\n@book{jensen2016c, title = {Introductory digital image processing: a remote sensing perspective}, author = {Jensen, John R.}, year = {2016}, date = {2016}, publisher = {Pearson Education}, series = {Pearson series in geographic information science}, edition = {Fourth edition}, address = {Glenview, Ill}, langid = {eng} }\n\n@article{radiativ2013, title = {Radiative transfer and atmospheric correction}, year = {2013}, month = {07}, date = {2013-07-19}, url = {[https://www.youtube.com/watch?v=qb4yFwzsnU8}](https://www.youtube.com/watch?v=qb4yFwzsnU8}) }\n\n@misc{ceosana, title = {CEOS Analysis Ready Data}, url = {[https://ceos.org/ard/},](https://ceos.org/ard/},) langid = {en} }\n\n@book{jensen2016d, title = {Introductory digital image processing: a remote sensing perspective}, author = {Jensen, John R.}, year = {2016}, date = {2016}, publisher = {Pearson Education}, series = {Pearson series in geographic information science}, edition = {Fourth edition}, address = {Glenview, Ill}, langid = {eng} }\n\n@misc{landsat2022, title = {Landsat Collection 2 Level-2 Science Products \\| U.S. Geological Survey}, year = {2022}, month = {11}, date = {2022-11-09}, url = {[https://www.usgs.gov/landsat-missions/landsat-collection-2-level-2-science-products},](https://www.usgs.gov/landsat-missions/landsat-collection-2-level-2-science-products},) langid = {en} }\n\n@book{jensen2016e, title = {Introductory digital image processing: a remote sensing perspective}, author = {Jensen, John R.}, year = {2016}, date = {2016}, publisher = {Pearson Education}, series = {Pearson series in geographic information science}, edition = {Fourth edition}, address = {Glenview, Ill}, langid = {eng} }\n\n@misc{landsat2024, title = {Landsat 8-9 Collection 2 Level 2 Science Product Guide \\| U.S. Geological Survey}, year = {2024}, month = {05}, date = {2024-05-23}, url = {[https://www.usgs.gov/media/files/landsat-8-9-collection-2-level-2-science-product-guide},](https://www.usgs.gov/media/files/landsat-8-9-collection-2-level-2-science-product-guide},) langid = {en} }\n\n@article{orimoloye2019, title = {Spatial assessment of drought severity in Cape Town area, South Africa}, author = {Orimoloye, I.R. and Ololade, O.O. and Mazinyo, S.P. and Kalumba, A.M. and Ekundayo, O.Y. and Busayo, E.T. and Akinsanola, A.A. and Nel, W.}, year = {2019}, month = {07}, date = {2019-07}, journal = {Heliyon}, pages = {e02148}, volume = {5}, number = {7}, doi = {10.1016/j.heliyon.2019.e02148}, url = {[https://linkinghub.elsevier.com/retrieve/pii/S2405844019358086},](https://linkinghub.elsevier.com/retrieve/pii/S2405844019358086},) langid = {en} }\n\n@article{faridatul2018, title = {Automatic Classification of Major Urban Land Covers Based on Novel Spectral Indices}, author = {Faridatul, Mst Ilme and Wu, Bo}, year = {2018}, month = {11}, date = {2018-11-22}, journal = {ISPRS International Journal of Geo-Information}, pages = {453}, volume = {7}, number = {12}, doi = {10.3390/ijgi7120453}, url = {[https://www.mdpi.com/2220-9964/7/12/453},](https://www.mdpi.com/2220-9964/7/12/453},) langid = {en} }\n\n@book{jensen2016f, title = {Introductory digital image processing: a remote sensing perspective}, author = {Jensen, John R.}, year = {2016}, date = {2016}, publisher = {Pearson Education}, series = {Pearson series in geographic information science}, edition = {Fourth edition}, address = {Glenview, Ill}, langid = {eng} }\n\n@article{schultetobühne2018, title = {Better together: Integrating and fusing multispectral and radar satellite imagery to inform biodiversity monitoring, ecological research and conservation science}, author = {{Schulte To Bühne}, Henrike and Pettorelli, Nathalie}, editor = {Lecomte, Nicolas}, year = {2018}, month = {04}, date = {2018-04}, journal = {Methods in Ecology and Evolution}, pages = {849--865}, volume = {9}, number = {4}, doi = {10.1111/2041-210X.12942}, url = {[https://besjournals.onlinelibrary.wiley.com/doi/10.1111/2041-210X.12942},](https://besjournals.onlinelibrary.wiley.com/doi/10.1111/2041-210X.12942},) langid = {en} }\n\n@misc{landsat2024a, title = {Landsat 8-9 Collection 2 Level 2 Science Product Guide \\| U.S. Geological Survey}, year = {2024}, month = {05}, date = {2024-05-23}, url = {[https://www.usgs.gov/media/files/landsat-8-9-collection-2-level-2-science-product-guide},](https://www.usgs.gov/media/files/landsat-8-9-collection-2-level-2-science-product-guide},) langid = {en} }\n:::\n","srcMarkdownNoYaml":""},"formats":{"html":{"identifier":{"display-name":"HTML","target-format":"html","base-format":"html"},"execute":{"fig-width":7,"fig-height":5,"fig-format":"retina","fig-dpi":96,"df-print":"default","error":false,"eval":true,"cache":null,"freeze":false,"echo":true,"output":true,"warning":true,"include":true,"keep-md":false,"keep-ipynb":false,"ipynb":null,"enabled":null,"daemon":null,"daemon-restart":false,"debug":false,"ipynb-filters":[],"ipynb-shell-interactivity":null,"plotly-connected":true,"engine":"markdown"},"render":{"keep-tex":false,"keep-typ":false,"keep-source":false,"keep-hidden":false,"prefer-html":false,"output-divs":true,"output-ext":"html","fig-align":"default","fig-pos":null,"fig-env":null,"code-fold":"none","code-overflow":"scroll","code-link":false,"code-line-numbers":false,"code-tools":false,"tbl-colwidths":"auto","merge-includes":true,"inline-includes":false,"preserve-yaml":false,"latex-auto-mk":true,"latex-auto-install":true,"latex-clean":true,"latex-min-runs":1,"latex-max-runs":10,"latex-makeindex":"makeindex","latex-makeindex-opts":[],"latex-tlmgr-opts":[],"latex-input-paths":[],"latex-output-dir":null,"link-external-icon":false,"link-external-newwindow":false,"self-contained-math":false,"format-resources":[],"notebook-links":true},"pandoc":{"standalone":true,"wrap":"none","default-image-extension":"png","to":"html","output-file":"references.html"},"language":{"toc-title-document":"Table of contents","toc-title-website":"On this page","related-formats-title":"Other Formats","related-notebooks-title":"Notebooks","source-notebooks-prefix":"Source","other-links-title":"Other Links","code-links-title":"Code Links","launch-dev-container-title":"Launch Dev Container","launch-binder-title":"Launch Binder","article-notebook-label":"Article Notebook","notebook-preview-download":"Download Notebook","notebook-preview-download-src":"Download Source","notebook-preview-back":"Back to Article","manuscript-meca-bundle":"MECA Bundle","section-title-abstract":"Abstract","section-title-appendices":"Appendices","section-title-footnotes":"Footnotes","section-title-references":"References","section-title-reuse":"Reuse","section-title-copyright":"Copyright","section-title-citation":"Citation","appendix-attribution-cite-as":"For attribution, please cite this work as:","appendix-attribution-bibtex":"BibTeX citation:","appendix-view-license":"View License","title-block-author-single":"Author","title-block-author-plural":"Authors","title-block-affiliation-single":"Affiliation","title-block-affiliation-plural":"Affiliations","title-block-published":"Published","title-block-modified":"Modified","title-block-keywords":"Keywords","callout-tip-title":"Tip","callout-note-title":"Note","callout-warning-title":"Warning","callout-important-title":"Important","callout-caution-title":"Caution","code-summary":"Code","code-tools-menu-caption":"Code","code-tools-show-all-code":"Show All Code","code-tools-hide-all-code":"Hide All Code","code-tools-view-source":"View Source","code-tools-source-code":"Source Code","tools-share":"Share","tools-download":"Download","code-line":"Line","code-lines":"Lines","copy-button-tooltip":"Copy to Clipboard","copy-button-tooltip-success":"Copied!","repo-action-links-edit":"Edit this page","repo-action-links-source":"View source","repo-action-links-issue":"Report an issue","back-to-top":"Back to top","search-no-results-text":"No results","search-matching-documents-text":"matching documents","search-copy-link-title":"Copy link to search","search-hide-matches-text":"Hide additional matches","search-more-match-text":"more match in this document","search-more-matches-text":"more matches in this document","search-clear-button-title":"Clear","search-text-placeholder":"","search-detached-cancel-button-title":"Cancel","search-submit-button-title":"Submit","search-label":"Search","toggle-section":"Toggle section","toggle-sidebar":"Toggle sidebar navigation","toggle-dark-mode":"Toggle dark mode","toggle-reader-mode":"Toggle reader mode","toggle-navigation":"Toggle navigation","crossref-fig-title":"Figure","crossref-tbl-title":"Table","crossref-lst-title":"Listing","crossref-thm-title":"Theorem","crossref-lem-title":"Lemma","crossref-cor-title":"Corollary","crossref-prp-title":"Proposition","crossref-cnj-title":"Conjecture","crossref-def-title":"Definition","crossref-exm-title":"Example","crossref-exr-title":"Exercise","crossref-ch-prefix":"Chapter","crossref-apx-prefix":"Appendix","crossref-sec-prefix":"Section","crossref-eq-prefix":"Equation","crossref-lof-title":"List of Figures","crossref-lot-title":"List of Tables","crossref-lol-title":"List of Listings","environment-proof-title":"Proof","environment-remark-title":"Remark","environment-solution-title":"Solution","listing-page-order-by":"Order By","listing-page-order-by-default":"Default","listing-page-order-by-date-asc":"Oldest","listing-page-order-by-date-desc":"Newest","listing-page-order-by-number-desc":"High to Low","listing-page-order-by-number-asc":"Low to High","listing-page-field-date":"Date","listing-page-field-title":"Title","listing-page-field-description":"Description","listing-page-field-author":"Author","listing-page-field-filename":"File Name","listing-page-field-filemodified":"Modified","listing-page-field-subtitle":"Subtitle","listing-page-field-readingtime":"Reading Time","listing-page-field-wordcount":"Word Count","listing-page-field-categories":"Categories","listing-page-minutes-compact":"{0} min","listing-page-category-all":"All","listing-page-no-matches":"No matching items","listing-page-words":"{0} words","listing-page-filter":"Filter","draft":"Draft"},"metadata":{"lang":"en","fig-responsive":true,"quarto-version":"1.8.27","bibliography":["references.bib"],"editor":"visual","theme":["cosmo","brand"]},"extensions":{"book":{"multiFile":true}}},"pdf":{"identifier":{"display-name":"PDF","target-format":"pdf","base-format":"pdf"},"execute":{"fig-width":5.5,"fig-height":3.5,"fig-format":"pdf","fig-dpi":300,"df-print":"default","error":false,"eval":true,"cache":null,"freeze":false,"echo":true,"output":true,"warning":true,"include":true,"keep-md":false,"keep-ipynb":false,"ipynb":null,"enabled":null,"daemon":null,"daemon-restart":false,"debug":false,"ipynb-filters":[],"ipynb-shell-interactivity":null,"plotly-connected":true,"engine":"markdown"},"render":{"keep-tex":false,"keep-typ":false,"keep-source":false,"keep-hidden":false,"prefer-html":false,"output-divs":true,"output-ext":"pdf","fig-align":"default","fig-pos":null,"fig-env":null,"code-fold":"none","code-overflow":"scroll","code-link":false,"code-line-numbers":false,"code-tools":false,"tbl-colwidths":true,"merge-includes":true,"inline-includes":false,"preserve-yaml":false,"latex-auto-mk":true,"latex-auto-install":true,"latex-clean":true,"latex-min-runs":1,"latex-max-runs":10,"latex-makeindex":"makeindex","latex-makeindex-opts":[],"latex-tlmgr-opts":[],"latex-input-paths":[],"latex-output-dir":null,"link-external-icon":false,"link-external-newwindow":false,"self-contained-math":false,"format-resources":[]},"pandoc":{"pdf-engine":"lualatex","standalone":true,"variables":{"graphics":true,"tables":true},"default-image-extension":"pdf","to":"pdf","output-file":"references.pdf"},"language":{"toc-title-document":"Table of contents","toc-title-website":"On this page","related-formats-title":"Other Formats","related-notebooks-title":"Notebooks","source-notebooks-prefix":"Source","other-links-title":"Other Links","code-links-title":"Code Links","launch-dev-container-title":"Launch Dev Container","launch-binder-title":"Launch Binder","article-notebook-label":"Article Notebook","notebook-preview-download":"Download Notebook","notebook-preview-download-src":"Download Source","notebook-preview-back":"Back to Article","manuscript-meca-bundle":"MECA Bundle","section-title-abstract":"Abstract","section-title-appendices":"Appendices","section-title-footnotes":"Footnotes","section-title-references":"References","section-title-reuse":"Reuse","section-title-copyright":"Copyright","section-title-citation":"Citation","appendix-attribution-cite-as":"For attribution, please cite this work as:","appendix-attribution-bibtex":"BibTeX citation:","appendix-view-license":"View License","title-block-author-single":"Author","title-block-author-plural":"Authors","title-block-affiliation-single":"Affiliation","title-block-affiliation-plural":"Affiliations","title-block-published":"Published","title-block-modified":"Modified","title-block-keywords":"Keywords","callout-tip-title":"Tip","callout-note-title":"Note","callout-warning-title":"Warning","callout-important-title":"Important","callout-caution-title":"Caution","code-summary":"Code","code-tools-menu-caption":"Code","code-tools-show-all-code":"Show All Code","code-tools-hide-all-code":"Hide All Code","code-tools-view-source":"View Source","code-tools-source-code":"Source Code","tools-share":"Share","tools-download":"Download","code-line":"Line","code-lines":"Lines","copy-button-tooltip":"Copy to Clipboard","copy-button-tooltip-success":"Copied!","repo-action-links-edit":"Edit this page","repo-action-links-source":"View source","repo-action-links-issue":"Report an issue","back-to-top":"Back to top","search-no-results-text":"No results","search-matching-documents-text":"matching documents","search-copy-link-title":"Copy link to search","search-hide-matches-text":"Hide additional matches","search-more-match-text":"more match in this document","search-more-matches-text":"more matches in this document","search-clear-button-title":"Clear","search-text-placeholder":"","search-detached-cancel-button-title":"Cancel","search-submit-button-title":"Submit","search-label":"Search","toggle-section":"Toggle section","toggle-sidebar":"Toggle sidebar navigation","toggle-dark-mode":"Toggle dark mode","toggle-reader-mode":"Toggle reader mode","toggle-navigation":"Toggle navigation","crossref-fig-title":"Figure","crossref-tbl-title":"Table","crossref-lst-title":"Listing","crossref-thm-title":"Theorem","crossref-lem-title":"Lemma","crossref-cor-title":"Corollary","crossref-prp-title":"Proposition","crossref-cnj-title":"Conjecture","crossref-def-title":"Definition","crossref-exm-title":"Example","crossref-exr-title":"Exercise","crossref-ch-prefix":"Chapter","crossref-apx-prefix":"Appendix","crossref-sec-prefix":"Section","crossref-eq-prefix":"Equation","crossref-lof-title":"List of Figures","crossref-lot-title":"List of Tables","crossref-lol-title":"List of Listings","environment-proof-title":"Proof","environment-remark-title":"Remark","environment-solution-title":"Solution","listing-page-order-by":"Order By","listing-page-order-by-default":"Default","listing-page-order-by-date-asc":"Oldest","listing-page-order-by-date-desc":"Newest","listing-page-order-by-number-desc":"High to Low","listing-page-order-by-number-asc":"Low to High","listing-page-field-date":"Date","listing-page-field-title":"Title","listing-page-field-description":"Description","listing-page-field-author":"Author","listing-page-field-filename":"File Name","listing-page-field-filemodified":"Modified","listing-page-field-subtitle":"Subtitle","listing-page-field-readingtime":"Reading Time","listing-page-field-wordcount":"Word Count","listing-page-field-categories":"Categories","listing-page-minutes-compact":"{0} min","listing-page-category-all":"All","listing-page-no-matches":"No matching items","listing-page-words":"{0} words","listing-page-filter":"Filter","draft":"Draft"},"metadata":{"block-headings":true,"bibliography":["references.bib"],"editor":"visual","documentclass":"scrreprt"},"extensions":{"book":{"selfContainedOutput":true}}}},"projectFormats":["html","pdf"]}